colcon_override_check/__init__.py
colcon_override_check/package_selection/__init__.py
colcon_override_check/package_selection/override_check.py
colcon_override_check-0.0.1.dist-info/DESCRIPTION.rst
colcon_override_check-0.0.1.dist-info/METADATA
colcon_override_check-0.0.1.dist-info/RECORD
colcon_override_check-0.0.1.dist-info/WHEEL
colcon_override_check-0.0.1.dist-info/entry_points.txt
colcon_override_check-0.0.1.dist-info/metadata.json
colcon_override_check-0.0.1.dist-info/top_level.txt
colcon_override_check-0.0.1.dist-info/zip-safe
